{"batch_id": 37, "start_block": 22100000, "end_block": 22121000, "distribution": [{"gas_bucket": 21000, "transaction_count": 872589, "min_gas": 21000, "max_gas": 21000, "avg_gas": 21000.0}, {"gas_bucket": 50000, "transaction_count": 449036, "min_gas": 21001, "max_gas": 50000, "avg_gas": 35410.68599176903}, {"gas_bucket": 100000, "transaction_count": 686314, "min_gas": 50001, "max_gas": 100000, "avg_gas": 75009.33097824028}, {"gas_bucket": 200000, "transaction_count": 291571, "min_gas": 100001, "max_gas": 200000, "avg_gas": 154662.02763649335}, {"gas_bucket": 500000, "transaction_count": 650987, "min_gas": 200001, "max_gas": 500000, "avg_gas": 306978.2227049081}, {"gas_bucket": 1000000, "transaction_count": 143568, "min_gas": 500001, "max_gas": 1000000, "avg_gas": 732024.7320712137}, {"gas_bucket": 2000000, "transaction_count": 62040, "min_gas": 1000001, "max_gas": 2000000, "avg_gas": 1415659.6330754352}, {"gas_bucket": 5000000, "transaction_count": 23064, "min_gas": 2000001, "max_gas": 5000000, "avg_gas": 3247755.7691640654}, {"gas_bucket": 10000000, "transaction_count": 8958, "min_gas": 5001286, "max_gas": 10000000, "avg_gas": 6472144.915159633}, {"gas_bucket": 16777216, "transaction_count": 5226, "min_gas": 10000100, "max_gas": 16749451, "avg_gas": 11841870.84041332}, {"gas_bucket": 20000000, "transaction_count": 585, "min_gas": 16849356, "max_gas": 20000000, "avg_gas": 19028595.586324785}, {"gas_bucket": 30000000, "transaction_count": 2482, "min_gas": 20020362, "max_gas": 30000000, "avg_gas": 24271401.946011283}, {"gas_bucket": 30000001, "transaction_count": 970, "min_gas": 30066665, "max_gas": 35860293, "avg_gas": 32801691.770103093}]}